[
  {"name": "name", "type": "string", "title": "Name"},
  {"name": "native_name", "type": "string", "title": "Native name"},
  {"name": "flag", "type": "string", "title": "Flag"},
  {"name": "coat_of_arms", "type": "string", "title": "Coat of arms"},
  {"name": "image", "type": "string", "title": "Image"},
  {"name": "caption", "type": "string", "title": "Caption"},
  {"name": "country", "type": "string", "title": "Country"},
  {"name": "region", "type": "string", "title": "Region"},
  {"name": "settlement_type", "type": "string", "title": "Settlement type"},
  {"name": "area_km2", "type": "number", "title": "Area km²"},
  {"name": "population", "type": "number", "title": "Population"},
  {"name": "metro_population", "type": "number", "title": "Metro population"},
  {"name": "coords", "type": "string", "title": "Coords"},
  {"name": "elevation_m", "type": "number", "title": "Elevation m"},
  {"name": "timezone", "type": "string", "title": "Timezone"},
  {"name": "mayor", "type": "string", "title": "Mayor"},
  {"name": "founded", "type": "string", "title": "Founded"},
  {"name": "founder", "type": "string", "title": "Founder"},
  {"name": "administrative_division", "type": "string", "title": "Administrative division"},
  {"name": "postal_code", "type": "string", "title": "Postal code"},
  {"name": "area_code", "type": "string", "title": "Area code"},
  {"name": "vehicle_registration", "type": "string", "title": "Vehicle registration"},
  {"name": "map", "type": "string", "title": "Map"},
  {"name": "website", "type": "string", "title": "Website"}
]
